pylint_plus/__init__.py
pylint_plus/function_order_checker.py
pylint_plus/magic_constant_checker.py
pylint_plus/return_method_checker.py
pylint_plus-0.0.2.dist-info/LICENSE
pylint_plus-0.0.2.dist-info/METADATA
pylint_plus-0.0.2.dist-info/WHEEL
pylint_plus-0.0.2.dist-info/top_level.txt
pylint_plus-0.0.2.dist-info/RECORD
